{
    "result": {
        "intCitiesList": [
            {
                "CityCode": "PAR",
                "GeoId": "F00205",
                "CountryName": "法国",
                "StateName": "法兰西岛大区",
                "StateCode": "FR法兰西岛大区",
                "CityEnName": "Paris",
                "CityName": "巴黎",
                "CountryEnName": "France",
                "CountryCode": "FR",
                "StateEnName": "Ile De France"
            },
            {
                "CityCode": "FFT",
                "GeoId": "F01298",
                "CountryName": "美国",
                "StateName": "肯塔基州",
                "StateCode": "US肯塔基州",
                "CityEnName": "Frankfort",
                "CityName": "法兰克福",
                "CountryEnName": "The United States",
                "CountryCode": "US",
                "StateEnName": "Kentucky"
            },
            {
                "CityCode": "HKG",
                "GeoId": "F01603",
                "CountryName": "中国香港",
                "StateName": "香港",
                "StateCode": "HK香港",
                "CityEnName": "Hong Kong",
                "CityName": "香港",
                "CountryEnName": "Hong Kong",
                "CountryCode": "HK",
                "StateEnName": "Hong Kong"
            },
            {
                "CityCode": "KUL",
                "GeoId": "F02106",
                "CountryName": "马来西亚",
                "StateName": null,
                "StateCode": "MY",
                "CityEnName": "Kuala Lumpur",
                "CityName": "吉隆坡",
                "CountryEnName": "Malaysia",
                "CountryCode": "MY",
                "StateEnName": null
            },
            {
                "CityCode": "LON",
                "GeoId": "F02282",
                "CountryName": "英国",
                "StateName": "大伦敦",
                "StateCode": "GB大伦敦",
                "CityEnName": "London",
                "CityName": "伦敦",
                "CountryEnName": "United Kingdom",
                "CountryCode": "GB",
                "StateEnName": "Greater London"
            },
            {
                "CityCode": "LSQ",
                "GeoId": "F02319",
                "CountryName": "智利",
                "StateName": null,
                "StateCode": "CL",
                "CityEnName": "Los Angeles",
                "CityName": "洛杉矶",
                "CountryEnName": "Chile",
                "CountryCode": "CL",
                "StateEnName": null
            },
            {
                "CityCode": "SEL",
                "GeoId": "F03450",
                "CountryName": "韩国",
                "StateName": "首尔特别市",
                "StateCode": "KR首尔特别市",
                "CityEnName": "Seoul",
                "CityName": "首尔",
                "CountryEnName": "Korea South",
                "CountryCode": "KR",
                "StateEnName": "Seoul"
            },
            {
                "CityCode": "SIN",
                "GeoId": "F03488",
                "CountryName": "新加坡",
                "StateName": null,
                "StateCode": "SG",
                "CityEnName": "Singapore",
                "CityName": "新加坡",
                "CountryEnName": "Singapore",
                "CountryCode": "SG",
                "StateEnName": null
            },
            {
                "CityCode": "TPE",
                "GeoId": "F03857",
                "CountryName": "中国台湾",
                "StateName": "台湾",
                "StateCode": "TW台湾",
                "CityEnName": "Taipei",
                "CityName": "台北",
                "CountryEnName": "Taiwan, Province of",
                "CountryCode": "TW",
                "StateEnName": "Taiwan"
            },
            {
                "CityCode": "TYO",
                "GeoId": "F03922",
                "CountryName": "日本",
                "StateName": "东京都",
                "StateCode": "JP东京都",
                "CityEnName": "Tokyo",
                "CityName": "东京",
                "CountryEnName": "Japan",
                "CountryCode": "JP",
                "StateEnName": "Tokyo"
            },
            {
                "CityCode": "YVR",
                "GeoId": "F04488",
                "CountryName": "加拿大",
                "StateName": "不列颠哥伦比亚省",
                "StateCode": "CA不列颠哥伦比亚省",
                "CityEnName": "Vancouver",
                "CityName": "温哥华",
                "CountryEnName": "Canada",
                "CountryCode": "CA",
                "StateEnName": "British Columbia"
            },
            {
                "CityCode": "NGO",
                "GeoId": "F04814",
                "CountryName": "日本",
                "StateName": "爱知县",
                "StateCode": "JP爱知县",
                "CityEnName": "Nagoya",
                "CityName": "名古屋",
                "CountryEnName": "Japan",
                "CountryCode": "JP",
                "StateEnName": "Nagasaki"
            },
            {
                "CityCode": "BKK",
                "GeoId": "F05784",
                "CountryName": "泰国",
                "StateName": null,
                "StateCode": "TH",
                "CityEnName": "Bangkok",
                "CityName": "曼谷",
                "CountryEnName": "Thailand",
                "CountryCode": "TH",
                "StateEnName": null
            },
            {
                "CityCode": "MNL",
                "GeoId": "F07276",
                "CountryName": "菲律宾",
                "StateName": "马尼拉大都会",
                "StateCode": "PH马尼拉大都会",
                "CityEnName": "Manila",
                "CityName": "马尼拉",
                "CountryEnName": "Philippines",
                "CountryCode": "PH",
                "StateEnName": "Metro Manila"
            },
            {
                "CityCode": "NYC",
                "GeoId": "F07522",
                "CountryName": "美国",
                "StateName": "纽约州",
                "StateCode": "US纽约州",
                "CityEnName": "New York",
                "CityName": "纽约",
                "CountryEnName": "The United States",
                "CountryCode": "US",
                "StateEnName": "New York"
            },
            {
                "CityCode": "OSA",
                "GeoId": "F07643",
                "CountryName": "日本",
                "StateName": "大阪府",
                "StateCode": "JP大阪府",
                "CityEnName": "Osaka",
                "CityName": "大阪",
                "CountryEnName": "Japan",
                "CountryCode": "JP",
                "StateEnName": "Osaka"
            },
            {
                "CityCode": "PUS",
                "GeoId": "F07887",
                "CountryName": "韩国",
                "StateName": "釜山广域市",
                "StateCode": "KR釜山广域市",
                "CityEnName": "Busan",
                "CityName": "釜山",
                "CountryEnName": "Korea South",
                "CountryCode": "KR",
                "StateEnName": "Busan"
            },
            {
                "CityCode": "FRA",
                "GeoId": "F09525",
                "CountryName": "德国",
                "StateName": "黑森州",
                "StateCode": "DE黑森州",
                "CityEnName": "Frankfurt",
                "CityName": "法兰克福",
                "CountryEnName": "Germany",
                "CountryCode": "DE",
                "StateEnName": "Hessen"
            },
            {
                "CityCode": "LAX",
                "GeoId": "F09611",
                "CountryName": "美国",
                "StateName": "加利福尼亚州",
                "StateCode": "US加利福尼亚州",
                "CityEnName": "Los Angeles",
                "CityName": "洛杉矶",
                "CountryEnName": "The United States",
                "CountryCode": "US",
                "StateEnName": "California"
            },
            {
                "CityCode": "MXA",
                "GeoId": "F09668",
                "CountryName": "美国",
                "StateName": "犹他州",
                "StateCode": "US犹他州",
                "CityEnName": "Manila",
                "CityName": "马尼拉",
                "CountryEnName": "The United States",
                "CountryCode": "US",
                "StateEnName": "Utah"
            },
            {
                "CityCode": "YXU",
                "GeoId": "F09912",
                "CountryName": "加拿大",
                "StateName": "安大略省",
                "StateCode": "CA安大略省",
                "CityEnName": "London",
                "CityName": "伦敦",
                "CountryEnName": "Canada",
                "CountryCode": "CA",
                "StateEnName": "Ontario"
            },
            {
                "CityCode": "MFM",
                "GeoId": "F09999",
                "CountryName": "中国澳门",
                "StateName": "澳门",
                "StateCode": "MO澳门",
                "CityEnName": "Macau",
                "CityName": "澳门",
                "CountryEnName": "Macau SAR",
                "CountryCode": "MO",
                "StateEnName": "Macau"
            }
        ],
        "cnCitiesList": [
            {
                "CityCode": "TSN",
                "GeoId": "L00002",
                "CountryName": "中国",
                "StateName": "天津",
                "StateCode": "CN天津",
                "CityEnName": "Tianjin",
                "CityName": "天津名字超长我任性",
                "CountryEnName": "China",
                "CountryCode": "CN",
                "StateEnName": "Tianjin"
            },
            {
                "CityCode": "DLC",
                "GeoId": "L00336",
                "CountryName": "中国",
                "StateName": "辽宁",
                "StateCode": "CN辽宁",
                "CityEnName": "Dalian",
                "CityName": "大连五个字",
                "CountryEnName": "China",
                "CountryCode": "CN",
                "StateEnName": "Liaoning"
            },
            {
                "CityCode": "NKG",
                "GeoId": "L00510",
                "CountryName": "中国",
                "StateName": "江苏",
                "StateCode": "CN江苏",
                "CityEnName": "Nanjing",
                "CityName": "南京都说我最长，那我还真不客气了",
                "CountryEnName": "China",
                "CountryCode": "CN",
                "StateEnName": "Jiangsu"
            },
            {
                "CityCode": "HGH",
                "GeoId": "L00564",
                "CountryName": "中国",
                "StateName": "浙江",
                "StateCode": "CN浙江",
                "CityEnName": "Hangzhou",
                "CityName": "杭州",
                "CountryEnName": "China",
                "CountryCode": "CN",
                "StateEnName": "Zhejiang"
            },
            {
                "CityCode": "NGB",
                "GeoId": "L00569",
                "CountryName": "中国",
                "StateName": "浙江",
                "StateCode": "CN浙江",
                "CityEnName": "Ningbo",
                "CityName": "宁波",
                "CountryEnName": "China",
                "CountryCode": "CN",
                "StateEnName": "Zhejiang"
            },
            {
                "CityCode": "FOC",
                "GeoId": "L00706",
                "CountryName": "中国",
                "StateName": "福建",
                "StateCode": "CN福建",
                "CityEnName": "Fuzhou",
                "CityName": "福州",
                "CountryEnName": "China",
                "CountryCode": "CN",
                "StateEnName": "Fujian"
            },
            {
                "CityCode": "XMN",
                "GeoId": "L00715",
                "CountryName": "中国",
                "StateName": "福建",
                "StateCode": "CN福建",
                "CityEnName": "Xiamen",
                "CityName": "厦门",
                "CountryEnName": "China",
                "CountryCode": "CN",
                "StateEnName": "Fujian"
            },
            {
                "CityCode": "TNA",
                "GeoId": "L00861",
                "CountryName": "中国",
                "StateName": "山东",
                "StateCode": "CN山东",
                "CityEnName": "Jinan",
                "CityName": "济南",
                "CountryEnName": "China",
                "CountryCode": "CN",
                "StateEnName": "Shandong"
            },
            {
                "CityCode": "TAO",
                "GeoId": "L00866",
                "CountryName": "中国",
                "StateName": "山东",
                "StateCode": "CN山东",
                "CityEnName": "Qingdao",
                "CityName": "青岛",
                "CountryEnName": "China",
                "CountryCode": "CN",
                "StateEnName": "Shandong"
            },
            {
                "CityCode": "CGO",
                "GeoId": "L00962",
                "CountryName": "中国",
                "StateName": "河南",
                "StateCode": "CN河南",
                "CityEnName": "Zhengzhou",
                "CityName": "郑州",
                "CountryEnName": "China",
                "CountryCode": "CN",
                "StateEnName": "Hena"
            },
            {
                "CityCode": "WUH",
                "GeoId": "L01086",
                "CountryName": "中国",
                "StateName": "湖北",
                "StateCode": "CN湖北",
                "CityEnName": "Wuhan",
                "CityName": "武汉",
                "CountryEnName": "China",
                "CountryCode": "CN",
                "StateEnName": "Hubei"
            },
            {
                "CityCode": "CSX",
                "GeoId": "L01162",
                "CountryName": "中国",
                "StateName": "湖南",
                "StateCode": "CN湖南",
                "CityEnName": "Changsha",
                "CityName": "长沙",
                "CountryEnName": "China",
                "CountryCode": "CN",
                "StateEnName": "Huna"
            },
            {
                "CityCode": "CAN",
                "GeoId": "L01262",
                "CountryName": "中国",
                "StateName": "广东",
                "StateCode": "CN广东",
                "CityEnName": "Guangzhou",
                "CityName": "广州",
                "CountryEnName": "China",
                "CountryCode": "CN",
                "StateEnName": "Guangdong"
            },
            {
                "CityCode": "SZX",
                "GeoId": "L01271",
                "CountryName": "中国",
                "StateName": "广东",
                "StateCode": "CN广东",
                "CityEnName": "Shenzhen",
                "CityName": "深圳",
                "CountryEnName": "China",
                "CountryCode": "CN",
                "StateEnName": "Guangdong"
            },
            {
                "CityCode": "SYX",
                "GeoId": "L01427",
                "CountryName": "中国",
                "StateName": "海南",
                "StateCode": "CN海南",
                "CityEnName": "Sanya",
                "CityName": "三亚",
                "CountryEnName": "China",
                "CountryCode": "CN",
                "StateEnName": "Haina"
            },
            {
                "CityCode": "CKG",
                "GeoId": "L01445",
                "CountryName": "中国",
                "StateName": "重庆",
                "StateCode": "CN重庆",
                "CityEnName": "Chongqing",
                "CityName": "重庆",
                "CountryEnName": "China",
                "CountryCode": "CN",
                "StateEnName": "Chongqing"
            },
            {
                "CityCode": "CTU",
                "GeoId": "L01460",
                "CountryName": "中国",
                "StateName": "四川",
                "StateCode": "CN四川",
                "CityEnName": "Chengdu",
                "CityName": "成都",
                "CountryEnName": "China",
                "CountryCode": "CN",
                "StateEnName": "Sichuan"
            }
        ]
    },
    "errno": "0",
    "errmsg": "获取热门城市"
}